alist/__init__.py
alist/__main__.py
alist/error.py
alist/main.py
alist/model.py
alist/py.typed
alist/sync.py
alist/utils.py
alist/cli/__init__.py
alist/cli/_data.py
alist/cli/auth.py
tests/test_base.py
tests/test_sync.py
tests/test_utils.py
alist3-1.3.8.dist-info/METADATA
alist3-1.3.8.dist-info/WHEEL
alist3-1.3.8.dist-info/entry_points.txt
alist3-1.3.8.dist-info/top_level.txt
alist3-1.3.8.dist-info/RECORD
