Metadata-Version: 2.4
Name: alist3
Version: 1.3.8
Summary: AList V3 PythonSDK
Author-email: MoYan <moyanjdc@qq.com>
License: LGPL 2.1
Keywords: AList,PythonSDK,API
Classifier: Development Status :: 5 - Production/Stable
Classifier: Intended Audience :: Developers
Classifier: Topic :: Software Development :: Libraries
Classifier: License :: OSI Approved :: MIT License
Classifier: Programming Language :: Python
Classifier: Programming Language :: Python :: 3
Classifier: Programming Language :: Python :: 3.9
Classifier: Programming Language :: Python :: 3.10
Classifier: Programming Language :: Python :: 3.11
Classifier: Programming Language :: Python :: 3.12
Classifier: Programming Language :: Python :: 3.13
Classifier: Topic :: Utilities
Classifier: Natural Language :: English
Classifier: Natural Language :: Chinese (Simplified)
Requires-Python: >=3.9
Requires-Dist: aiohttp
Requires-Dist: aiofiles
Requires-Dist: platformdirs
Provides-Extra: cli
Requires-Dist: asyncclick; extra == "cli"
Requires-Dist: rich; extra == "cli"
